{
  "users": [
    {
      "id": 1,
      "name": "Joe Blogs",
      "email": "Joe.B@ac.me"
    },
    {
      "name": "hhh",
      "email": "ydytd@srx.ut",
      "id": 2
    }
  ],
  "note": [
    {
      "id": 1,
      "title": "Note 1",
      "text": "Ajndkcjnsdc sckjnasckjansc asckj asckjasckjas caas."
    },
    {
      "id": 2,
      "title": "Note 2",
      "text": "Bjndkcjnsdc sckjnasckjansc asckj asckjasckjas caas."
    },
    {
      "id": 3,
      "title": "Note 3a",
      "text": "Cjndkcjnsdc ccccccc"
    },
    {
      "title": "Note 5",
      "text": "Ensdconsdoc sdovj sdv",
      "id": 855407
    },
    {
      "title": "Note 7",
      "text": "Bla bla bla",
      "id": 20
    },
    {
      "title": "Note 8b",
      "text": "aaaaa bbbb ccc",
      "id": 614267
    }
  ]
}